re_extensions/__init__.py
re_extensions/__version__.py
re_extensions/_typing.py
re_extensions/core.py
re_extensions/smart.py
re_extensions-0.0.8.dist-info/LICENSE
re_extensions-0.0.8.dist-info/METADATA
re_extensions-0.0.8.dist-info/WHEEL
re_extensions-0.0.8.dist-info/top_level.txt
re_extensions-0.0.8.dist-info/RECORD
